vkbasalt/__init__.py
vkbasalt/cli.py
vkbasalt/lib.py
vkbasalt_cli-3.1.1.post2.dist-info/COPYING
vkbasalt_cli-3.1.1.post2.dist-info/COPYING.GPLv3
vkbasalt_cli-3.1.1.post2.dist-info/COPYING.LGPLv3
vkbasalt_cli-3.1.1.post2.dist-info/METADATA
vkbasalt_cli-3.1.1.post2.dist-info/WHEEL
vkbasalt_cli-3.1.1.post2.dist-info/entry_points.txt
vkbasalt_cli-3.1.1.post2.dist-info/top_level.txt
vkbasalt_cli-3.1.1.post2.dist-info/RECORD
