Metadata-Version: 2.1
Name: vkbasalt-cli
Version: 3.1.1.post2
Summary: A utility to pass arguments to vkBasalt
Author-email: TheEvilSkeleton <theevilskeleton@riseup.net>
Project-URL: Homepage, https://gitlab.com/TheEvilSkeleton/vkbasalt-cli
Project-URL: Bug Tracker, https://gitlab.com/TheEvilSkeleton/vkbasalt-cli/-/issues
Classifier: Programming Language :: Python :: 3
Classifier: License :: OSI Approved :: GNU General Public License v3 (GPLv3)
Classifier: License :: OSI Approved :: GNU Lesser General Public License v3 (LGPLv3)
Classifier: Operating System :: OS Independent
Classifier: Environment :: Console
Classifier: Topic :: Utilities
Requires-Python: >=3.8
License-File: COPYING
License-File: COPYING.GPLv3
License-File: COPYING.LGPLv3
